easyfsl/__init__.py
easyfsl/utils.py
easyfsl/datasets/__init__.py
easyfsl/datasets/cub.py
easyfsl/datasets/danish_fungi.py
easyfsl/datasets/default_configs.py
easyfsl/datasets/easy_set.py
easyfsl/datasets/features_dataset.py
easyfsl/datasets/few_shot_dataset.py
easyfsl/datasets/mini_imagenet.py
easyfsl/datasets/support_set_folder.py
easyfsl/datasets/tiered_imagenet.py
easyfsl/datasets/wrap_few_shot_dataset.py
easyfsl/methods/__init__.py
easyfsl/methods/bd_cspn.py
easyfsl/methods/feat.py
easyfsl/methods/few_shot_classifier.py
easyfsl/methods/finetune.py
easyfsl/methods/laplacian_shot.py
easyfsl/methods/matching_networks.py
easyfsl/methods/prototypical_networks.py
easyfsl/methods/pt_map.py
easyfsl/methods/relation_networks.py
easyfsl/methods/simple_shot.py
easyfsl/methods/tim.py
easyfsl/methods/transductive_finetuning.py
easyfsl/methods/utils.py
easyfsl/modules/__init__.py
easyfsl/modules/attention_modules.py
easyfsl/modules/build_from_checkpoint.py
easyfsl/modules/feat_resnet12.py
easyfsl/modules/predesigned_modules.py
easyfsl/modules/resnet.py
easyfsl/samplers/__init__.py
easyfsl/samplers/task_sampler.py
easyfsl/tests/__init__.py
easyfsl/tests/utils_test.py
easyfsl/tests/datasets/__init__.py
easyfsl/tests/datasets/easy_set_test.py
easyfsl/tests/datasets/features_dataset_test.py
easyfsl/tests/datasets/support_set_folder_test.py
easyfsl/tests/datasets/wrap_few_shot_dataset_test.py
easyfsl/tests/methods/__init__.py
easyfsl/tests/methods/conftest.py
easyfsl/tests/methods/feat_test.py
easyfsl/tests/methods/few_shot_classifier_test.py
easyfsl/tests/methods/finetuning_methods_test.py
easyfsl/tests/methods/matching_networks_test.py
easyfsl/tests/methods/prototypical_networks_test.py
easyfsl/tests/methods/relation_networks_test.py
easyfsl/tests/modules/__init__.py
easyfsl/tests/modules/predesigned_modules_test.py
easyfsl/tests/modules/resnet_test.py
easyfsl/tests/samplers/__init__.py
easyfsl/tests/samplers/task_sampler_test.py
scripts/__init__.py
easyfsl-1.5.0.dist-info/LICENSE
easyfsl-1.5.0.dist-info/METADATA
easyfsl-1.5.0.dist-info/WHEEL
easyfsl-1.5.0.dist-info/top_level.txt
easyfsl-1.5.0.dist-info/RECORD
