Metadata-Version: 2.1
Name: easyfsl
Version: 1.5.0
Summary: Ready-to-use PyTorch code to boost your way into few-shot image classification
Home-page: https://github.com/sicara/easy-few-shot-learning
License: MIT
Classifier: Development Status :: 3 - Alpha
Classifier: License :: OSI Approved :: MIT License
Classifier: Programming Language :: Python
Classifier: Programming Language :: Python :: 3
Classifier: Programming Language :: Python :: 3.7
Classifier: Programming Language :: Python :: 3.8
Classifier: Programming Language :: Python :: 3.9
Classifier: Programming Language :: Python :: 3.10
Classifier: Programming Language :: Python :: 3.11
Classifier: Operating System :: OS Independent
Requires-Python: >=3.6
License-File: LICENSE
Requires-Dist: matplotlib (>=3.0.0)
Requires-Dist: pandas (>=1.5.0)
Requires-Dist: torch (>=1.5.0)
Requires-Dist: torchvision (>=0.7.0)
Requires-Dist: tqdm (>=4.1.0)
